<?xml version="1.0" encoding="utf-8"?>
<search>
  
  
  
  <entry>
    <title>关于坚持</title>
    <link href="/2022/04/18/guanyujianchi/"/>
    <url>/2022/04/18/guanyujianchi/</url>
    
    <content type="html"><![CDATA[<p>ARTS是Algorithm, Review, Tip, Share的简写，源于一个编程算法训练计划。主要含义是：每周做一道算法题目；每周阅读一篇技术文章；每周学习一个技术技巧；每周分享一篇技术文章。心里又暗暗下定决心要试一试。是的,又是一个有关坚持的故事…</p><img src="/2022/04/18/guanyujianchi/keep.jpg" class="" title="keep"><p>关于坚持，很喜欢健身软件KEEP的宣传语“自律给我自由”。曾经我也有很多很多计划，坚持记日记、坚持读书、坚持健身、坚持写博客……定了好多计划很少有能坚持下来的，过程中还多了许多焦虑和挫败感。在我身上关于坚持和放弃的剧情还在反复上演。似乎还没有达到一个很好的平衡。但是一个平和包容的态度能让你更加积极面对，一步步进步。</p><p>知乎上KY(KnowYoutself)回答过关于“如何坚持做好一件事？”：1）选择一件适合坚持的事；2） 学会一些可行的方法。“合适”包括吸引力足够强（兴趣使然，目标价值对自己而言高等），阶段性的可实现，可执行性（目标足够细化）。可行的方法主要是抛开具体事情针对思维和行动上的方法。思维上包括与过去和未来的自己共情，放下对完美主义式的坚持等；行动上建立激励机制和社会强化等。</p><p>静心想想，很多计划定的有点高，让自己成了苦行僧，结果没能坚持下来，留下的挫败感反而增加了自己的负面情绪。似乎不停的在轮回……当心态改变，就能够泰然自若，平静对待。健身不一定要减肥，看书不一定要增长专业技术，写博客不一定要按固定频率等等，少一些功利反而更能坚持下来了。与过去的自己和解，“我与我周旋久，宁作我”。</p><p>最后借KY的原回答送给即将初三的妹妹<br>引用：<a href="https://www.zhihu.com/question/304988611/answer/569852651">如何长期坚持做好一件事？ - KnowYourself的回答 - 知乎</a></p><p>坚持这件事，美在你努力地跨过了漫漫岁月；坚持并不会因为你一次的失误、一次的懈怠就彻底失败，关键的是，要允许自己在坚持的过程中有犹豫、有懈怠、有一时的失败。<br>因为长时间的坚持常常是，你有时走得快、有时走得慢，有时在前进、有时在后退，无论多么曲曲折折，你仍在一点点坚持在路上，离最后的目的地越来越近。</p>]]></content>
    
    
    <categories>
      
      <category>读书</category>
      
    </categories>
    
    
    <tags>
      
      <tag>随笔</tag>
      
    </tags>
    
  </entry>
  
  
  
  <entry>
    <title>Hello World</title>
    <link href="/2022/04/18/hello-world/"/>
    <url>/2022/04/18/hello-world/</url>
    
    <content type="html"><![CDATA[<p>Welcome to <a href="https://hexo.io/">Hexo</a>! This is your very first post. Check <a href="https://hexo.io/docs/">documentation</a> for more info. If you get any problems when using Hexo, you can find the answer in <a href="https://hexo.io/docs/troubleshooting.html">troubleshooting</a> or you can ask me on <a href="https://github.com/hexojs/hexo/issues">GitHub</a>.</p><h2 id="Quick-Start"><a href="#Quick-Start" class="headerlink" title="Quick Start"></a>Quick Start</h2><h3 id="Create-a-new-post"><a href="#Create-a-new-post" class="headerlink" title="Create a new post"></a>Create a new post</h3><figure class="highlight bash"><table><tr><td class="gutter"><div class="code-wrapper"><pre><span class="line">1</span><br></pre></div></td><td class="code"><pre><code class="hljs bash">$ hexo new <span class="hljs-string">&quot;My New Post&quot;</span><br></code></pre></td></tr></table></figure><p>More info: <a href="https://hexo.io/docs/writing.html">Writing</a></p><h3 id="Run-server"><a href="#Run-server" class="headerlink" title="Run server"></a>Run server</h3><figure class="highlight bash"><table><tr><td class="gutter"><pre><span class="line">1</span><br></pre></td><td class="code"><pre><code class="hljs bash">$ hexo server<br></code></pre></td></tr></table></figure><p>More info: <a href="https://hexo.io/docs/server.html">Server</a></p><h3 id="Generate-static-files"><a href="#Generate-static-files" class="headerlink" title="Generate static files"></a>Generate static files</h3><figure class="highlight bash"><table><tr><td class="gutter"><pre><span class="line">1</span><br></pre></td><td class="code"><pre><code class="hljs bash">$ hexo generate<br></code></pre></td></tr></table></figure><p>More info: <a href="https://hexo.io/docs/generating.html">Generating</a></p><h3 id="Deploy-to-remote-sites"><a href="#Deploy-to-remote-sites" class="headerlink" title="Deploy to remote sites"></a>Deploy to remote sites</h3><figure class="highlight bash"><table><tr><td class="gutter"><pre><span class="line">1</span><br></pre></td><td class="code"><pre><code class="hljs bash">$ hexo deploy<br></code></pre></td></tr></table></figure><p>More info: <a href="https://hexo.io/docs/one-command-deployment.html">Deployment</a></p>]]></content>
    
    
    
  </entry>
  
  
  
  <entry>
    <title>毕业</title>
    <link href="/2020/06/19/biye/"/>
    <url>/2020/06/19/biye/</url>
    
    <content type="html"><![CDATA[<p>研究生三年时间很快，有收获，有遗憾，总的来说遗憾更多些。</p><span id="more"></span><p>入场踌躇满志，意气风发。出场结局平淡，些许遗憾。就个人的自我满足和充实而言。总结起来可以说是常怀一颗进取心，常行摸鱼打趣事。</p><p>毛伟人离家时写下“孩儿立志出乡关，学不成名誓不还。”的激扬文字，恰同学少年，风华正茂。我自不能企及半分，但是立足自己的规划还是有做过。之前开的公众号“研途Happy”也有做过些年度总结，学习规划等。然而一暴十寒。</p><p>利用闲暇之际给这个有些许遗憾的时光做一个总结。</p><p>无非两处，专业技能与综合修养。个人愚见，学习能力养成应是学习能力最重要的素养。深究一个研究方向有所建树最佳，期间养成适合自己的学习方法应该是研究生阶段最为重要的目标。要是给我的表现打分，十分满分只能得三四分。甚至于学习素养不及入学前的状态，三心二意没有认真做好一件科研工作。希望未来自己加油弥补遗憾。充实好未来的工作学习生活，我有信心。</p><p>说到自己的综合修养，相信自己能够比较好地适应小社会的生活。有人出世放飞自我，有人入世面善心伪，都有所体会，也为未来工作生活提供了经验。硕士期间两段感情都算是有些遗憾，是自己太作，在感情上还是不够成熟。今后切记不要意气用事，活的洒脱一些。要有男人该有的高亮品质和气节。</p><p>总觉的自己还是处于一个三观养成的阶段，应了屁股决定脑袋那句话。有很多关注到自己本身发展的东西都成了随波逐流。不忘初心方得始终，言之凿凿，行之艰难。写博客的想法也是希望自己可以坚持下来，给浮躁的自己一个冷静沉淀的时刻。</p><p>未来加油！</p><p>写于2020年6月19日</p>]]></content>
    
    
    <categories>
      
      <category>读书</category>
      
    </categories>
    
    
    <tags>
      
      <tag>随笔</tag>
      
    </tags>
    
  </entry>
  
  
  
  
</search>
